ipyaliplayer/__init__.py
ipyaliplayer/_frontend.py
ipyaliplayer/_version.py
ipyaliplayer/example.py
ipyaliplayer/labextension/ipyaliplayer-0.1.0.tgz
ipyaliplayer/labextension/ipyaliplayer-0.1.2.tgz
ipyaliplayer/labextension/ipyaliplayer-0.2.0.tgz
ipyaliplayer/labextension/ipyaliplayer-0.2.1.tgz
ipyaliplayer/labextension/ipyaliplayer-0.3.0.tgz
ipyaliplayer/labextension/ipyaliplayer-0.4.0.tgz
ipyaliplayer/labextension/ipyaliplayer-0.4.1.tgz
ipyaliplayer/nbextension/__init__.py
ipyaliplayer/nbextension/static/extension.js
ipyaliplayer/nbextension/static/index.js
ipyaliplayer/nbextension/static/index.js.map
ipyaliplayer/tests/__init__.py
ipyaliplayer/tests/conftest.py
ipyaliplayer/tests/test_example.py
ipyaliplayer/tests/test_nbextension_path.py
ipyaliplayer-0.4.1.data/data/etc/jupyter/nbconfig/notebook.d/ipyaliplayer.json
ipyaliplayer-0.4.1.data/data/share/jupyter/lab/extensions/ipyaliplayer-0.4.1.tgz
ipyaliplayer-0.4.1.data/data/share/jupyter/nbextensions/ipyaliplayer/extension.js
ipyaliplayer-0.4.1.data/data/share/jupyter/nbextensions/ipyaliplayer/index.js
ipyaliplayer-0.4.1.data/data/share/jupyter/nbextensions/ipyaliplayer/index.js.map
ipyaliplayer-0.4.1.dist-info/LICENSE.txt
ipyaliplayer-0.4.1.dist-info/METADATA
ipyaliplayer-0.4.1.dist-info/WHEEL
ipyaliplayer-0.4.1.dist-info/top_level.txt
ipyaliplayer-0.4.1.dist-info/RECORD
